<Properties StartupConfiguration="{7B2695D6-D24C-4460-A58E-A10F08550CE0}|Default">
  <MonoDevelop.Ide.ItemProperties.ExchangeRateUpdater PreferredExecutionTarget="MonoDevelop.Default" />
  <MonoDevelop.Ide.Workbench ActiveDocument="ExchangeRateProvider.cs">
    <Files>
      <File FileName="ExchangeRateProvider.cs" Line="75" Column="1" />
    </Files>
    <Pads>
      <Pad Id="ProjectPad">
        <State name="__root__">
          <Node name="ExchangeRateUpdater" expanded="True">
            <Node name="ExchangeRateUpdater" expanded="True">
              <Node name="ExchangeRateProvider.cs" selected="True" />
            </Node>
          </Node>
        </State>
      </Pad>
      <Pad Id="MonoDevelop.Debugger.WatchPad">
        <State />
      </Pad>
    </Pads>
  </MonoDevelop.Ide.Workbench>
  <MonoDevelop.Ide.DebuggingService.PinnedWatches />
  <MonoDevelop.Ide.Workspace ActiveConfiguration="Debug" />
  <MonoDevelop.Ide.DebuggingService.Breakpoints>
    <BreakpointStore />
  </MonoDevelop.Ide.DebuggingService.Breakpoints>
  <MultiItemStartupConfigurations />
</Properties>